mashwrapper
