Metadata-Version: 1.0
Name: mash-wrapper
Version: 1.0.5
Summary: This script runs MASH given a set of reads against specified references
Home-page: https://github.com/tiagofilipe12/mash_wrapper
Author: Tiago F. Jesus
Author-email: tiagojesus@medicina.ulisboa.pt
License: GPL3
Platform: UNKNOWN
